badx12/__init__.py
badx12/__main__.py
badx12/_settings.py
badx12/document.py
badx12/parser.py
badx12/commands/__init__.py
badx12/commands/parse/__init__.py
badx12/commands/parse/utils.py
badx12/common/__init__.py
badx12/common/click.py
badx12/common/paths.py
badx12/utils/__init__.py
badx12/utils/element.py
badx12/utils/envelope.py
badx12/utils/errors.py
badx12/utils/group.py
badx12/utils/interchange.py
badx12/utils/segment.py
badx12/utils/transaction_set.py
tests/__init__.py
tests/test_badx12.py
tests/utils.py
tests/files/edi/X221-dollars-and-data-sent-separate.edi
tests/files/edi/X221-dollars-and-data-sent-together.edi
tests/files/edi/X221-era-sample.edi
tests/files/edi/X221-multiple-claims-single-check.edi
tests/files/edi/X221-secondary-payment-with-higher-fee-schedule.edi
tests/files/edi/X221-secondary-payments.edi
tests/files/edi/X221-tertiary-payments.edi
tests/files/edi/X222-COB-claim-from-billing-provider-to-payer-a.edi
tests/files/edi/X222-COB-claim-from-billing-provider-to-payer-b.edi
tests/files/edi/X222-COB-claim-from-payer-a-to-payer-b-in-payer-to-payer.edi
tests/files/edi/X222-ambulance.edi
tests/files/edi/X222-anesthesia.edi
tests/files/edi/X222-chiropractic.edi
tests/files/edi/X222-commercial-health-insurance.edi
tests/files/edi/X222-drug-administered-in-the-physician-office.edi
tests/files/edi/X222-encounter.edi
tests/files/edi/X222-home-infusion-therapy-pharmacy-(adjudicated-with-HCPCS-in-loop-2400-or-NDC-in-loop-2410).edi
tests/files/edi/X222-home-infusion-therapy-pharmacy-(adjudicated-with-NDC-in-loop-2410).edi
tests/files/edi/X222-medicare-secondary-payer-COB.edi
tests/files/edi/X222-out-of-network-repriced-claim.edi
tests/files/edi/X222-oxygen.edi
tests/files/edi/X222-ppo-repriced-claim.edi
tests/files/edi/X222-wheelchair.edi
tests/files/edi/X279-error-response-from-payer-to-clinic-not-eligible-for-inquiries-with-payer.edi
tests/files/edi/X279-generic-request-by-clinic-for-patient-(subscriber)-eligibility.edi
badx12-0.2.2.dist-info/AUTHORS.rst
badx12-0.2.2.dist-info/LICENSE
badx12-0.2.2.dist-info/METADATA
badx12-0.2.2.dist-info/WHEEL
badx12-0.2.2.dist-info/entry_points.txt
badx12-0.2.2.dist-info/top_level.txt
badx12-0.2.2.dist-info/RECORD
