Metadata-Version: 2.1
Name: badx12
Version: 0.2.2
Summary: A Python Library for parsing ANSI ASC X12 files.
Home-page: https://github.com/git-albertomarin/badx12
Author: Alberto J. Marin
Author-email: alberto@ajmar.in
License: MIT license
Keywords: badx12 edi x12 parser
Platform: UNKNOWN
Classifier: Development Status :: 5 - Production/Stable
Classifier: Intended Audience :: Developers
Classifier: License :: OSI Approved :: MIT License
Classifier: Natural Language :: English
Classifier: Programming Language :: Python
Classifier: Programming Language :: Python :: 3.6
Classifier: Programming Language :: Python :: 3.7
Requires-Dist: click (==7.0)
Requires-Dist: dicttoxml (==1.7.4)
